GrammarEnhancer/__init__.py
GrammarEnhancer/dat.py
GrammarEnhancer-1.1.dist-info/LICENSE
GrammarEnhancer-1.1.dist-info/METADATA
GrammarEnhancer-1.1.dist-info/WHEEL
GrammarEnhancer-1.1.dist-info/top_level.txt
GrammarEnhancer-1.1.dist-info/RECORD
