Metadata-Version: 2.1
Name: GrammarEnhancer
Version: 1.1
Summary: Syntax Error Data Enhancement
Home-page: https://github.com/TW-NLP/CGED_DAT
Author: tianwei
Author-email: 1784526116@qq.com
Classifier: Programming Language :: Python :: 3
Classifier: License :: OSI Approved :: MIT License
Classifier: Operating System :: OS Independent
Requires-Python: >=3
License-File: LICENSE
Requires-Dist: ltp ==4.2.14
Requires-Dist: opencc ==1.1.6
